MANIFEST.in
setup.py
tapioca/__init__.py
tapioca/metadata.py
tapioca/request.py
tapioca/rest_api.py
tapioca/serializers.py
tapioca/spec.py
tapioca/visitor.py
tapioca.egg-info/PKG-INFO
tapioca.egg-info/SOURCES.txt
tapioca.egg-info/dependency_links.txt
tapioca.egg-info/requires.txt
tapioca.egg-info/top_level.txt
tapioca/templates/base.html
tapioca/templates/tapioca/resource.html