Metadata-Version: 1.0
Name: tapioca
Version: 0.1.21
Summary: Tapioca is a small and flexible micro-framework on top of Tornado. It provides a simpler way to create RESTful API's.
Home-page: https://github.com/globocom/tapioca
Author: globo.com
Author-email: lambda@corp.globo.com
License: MIT
Keywords: restful rest api tornado
Platform: UNKNOWN
Classifier: Development Status :: 4 - Beta
Classifier: Intended Audience :: Developers
Classifier: License :: OSI Approved :: MIT License
Classifier: Natural Language :: English
Classifier: Operating System :: MacOS
Classifier: Operating System :: POSIX :: Linux
Classifier: Programming Language :: Python :: 2.6
